restorething/__init__.py
restorething/__main__.py
restorething/_version.py
restorething/dbindex.py
restorething/dbrestore.py
restorething/restorething.py
restorething/rtdbtools.py
restorething/rtlog.py
restorething/rttools.py
restorething-0.2.3.dist-info/DESCRIPTION.rst
restorething-0.2.3.dist-info/METADATA
restorething-0.2.3.dist-info/RECORD
restorething-0.2.3.dist-info/WHEEL
restorething-0.2.3.dist-info/metadata.json
restorething-0.2.3.dist-info/top_level.txt
