Metadata-Version: 2.0
Name: restorething
Version: 0.2.3
Summary: restorething is a tool for restoring files from a syncthing versioning archive
Home-page: https://github.com/madmickstar/restorething
Author: Mick Shine
Author-email: madmixtar@gmail.com
License: MIT License
Requires-Dist: win-unicode-console (>=0.5)
